synth_zero/__init__.py
synth_zero/version.py
synth_zero-0.0.0.dist-info/licenses/LICENSE
synth_zero-0.0.0.dist-info/METADATA
synth_zero-0.0.0.dist-info/WHEEL
synth_zero-0.0.0.dist-info/entry_points.txt
synth_zero-0.0.0.dist-info/top_level.txt
synth_zero-0.0.0.dist-info/RECORD
